prompttrail/__init__.py
prompttrail/py.typed
prompttrail/agent/__init__.py
prompttrail/agent/py.typed
prompttrail/agent/runners.py
prompttrail/agent/user_interface.py
prompttrail/agent/session_transformers/__init__.py
prompttrail/agent/session_transformers/_code.py
prompttrail/agent/session_transformers/_core.py
prompttrail/agent/session_transformers/py.typed
prompttrail/agent/subroutine/__init__.py
prompttrail/agent/subroutine/_base.py
prompttrail/agent/subroutine/session_init_strategy.py
prompttrail/agent/subroutine/squash_strategy.py
prompttrail/agent/templates/__init__.py
prompttrail/agent/templates/_base.py
prompttrail/agent/templates/_control.py
prompttrail/agent/templates/_core.py
prompttrail/agent/templates/_tool.py
prompttrail/agent/templates/py.typed
prompttrail/agent/tools/__init__.py
prompttrail/agent/tools/_base.py
prompttrail/agent/tools/_subroutine.py
prompttrail/agent/tools/builtin.py
prompttrail/agent/tools/py.typed
prompttrail/core/__init__.py
prompttrail/core/cache.py
prompttrail/core/const.py
prompttrail/core/errors.py
prompttrail/core/mocks.py
prompttrail/core/py.typed
prompttrail/core/utils.py
prompttrail/models/__init__.py
prompttrail/models/anthropic.py
prompttrail/models/google.py
prompttrail/models/openai.py
prompttrail/models/py.typed
prompttrail/models/transformers.py
prompttrail-0.2.0.dist-info/METADATA
prompttrail-0.2.0.dist-info/WHEEL
prompttrail-0.2.0.dist-info/licenses/LICENCE
prompttrail-0.2.0.dist-info/RECORD
