Metadata-Version: 2.3
Name: prompttrail
Version: 0.2.0
Summary: A lightweight library for Prompt Programming: Agent as Code
Project-URL: Documentation, https://prompttrail.readthedocs.io
Project-URL: Repository, https://github.com/combinatrix-ai/PromptTrail
Author-email: hmirin <hmirin@example.com>
License: MIT
Classifier: Development Status :: 3 - Alpha
Classifier: Intended Audience :: Developers
Classifier: License :: OSI Approved :: MIT License
Classifier: Programming Language :: Python :: 3.11
Requires-Python: >=3.11
Requires-Dist: anthropic>=0.21.0
Requires-Dist: click>=8.1.7
Requires-Dist: google-generativeai>=0.4.1
Requires-Dist: jinja2>=3.1.2
Requires-Dist: openai>=1.14.2
Requires-Dist: pydantic>=2.6.4
Requires-Dist: tiktoken>=0.6.0
Requires-Dist: transformers>=4.44.2
Requires-Dist: types-cachetools>=5.3.0.7
Requires-Dist: typing-inspect>=0.9.0
